LICENSE
README.md
setup.py
llads/__init__.py
llads/customLLM.py
llads/tooling.py
llads/tools.py
llads/visualizations.py
llads.egg-info/PKG-INFO
llads.egg-info/SOURCES.txt
llads.egg-info/dependency_links.txt
llads.egg-info/top_level.txt