Metadata-Version: 2.1
Name: llads
Version: 0.0.12
Summary: LLM insights to data.
Home-page: https://github.com/dhopp1/llads
Author: Daniel Hopp
Author-email: daniel.hopp@un.org
Classifier: Programming Language :: Python :: 3
Classifier: License :: OSI Approved :: MIT License
Classifier: Operating System :: OS Independent
Requires-Python: >=3.6
License-File: LICENSE
